fy.py
signature.py
fixYabinary-0.3.0.data/scripts/fy
fixYabinary-0.3.0.dist-info/DESCRIPTION.rst
fixYabinary-0.3.0.dist-info/METADATA
fixYabinary-0.3.0.dist-info/RECORD
fixYabinary-0.3.0.dist-info/WHEEL
fixYabinary-0.3.0.dist-info/metadata.json
fixYabinary-0.3.0.dist-info/top_level.txt
