Metadata-Version: 2.0
Name: fixYabinary
Version: 0.3.0
Summary: Tool to Fix Yabinary File
Home-page: https://github.com/tkmru/fixYabinary
Author: @tkmru
Author-email: i.am.tkmru@gmail.com
License: MIT License
Keywords: binary,ctf
Platform: UNKNOWN
Classifier: Programming Language :: Python
Classifier: Programming Language :: Python :: 2
Classifier: Programming Language :: Python :: 3
Classifier: Operating System :: OS Independent
Classifier: License :: OSI Approved :: MIT License
